Metadata-Version: 2.1
Name: igor-tools
Version: 0.1.0
Summary: Simple tools to manage IGOR Pro .itx files
Home-page: https://github.com/nanotech-empa
License: UNKNOWN
Platform: UNKNOWN
Classifier: Programming Language :: Python :: 3
Classifier: License :: OSI Approved :: MIT License
Classifier: Operating System :: OS Independent
Requires-Python: >=3.6
